<annotation>
	<folder>train</folder>
	<filename>0621.jpg</filename>
	<path>E:\FPTdocument\Document\Machine Learning\VietAI_Advanced_CV\data_final\object-detection-Tensorflow\data\images\train\0621.jpg</path>
	<source>
		<database>Unknown</database>
	</source>
	<size>
		<width>1024</width>
		<height>606</height>
		<depth>3</depth>
	</size>
	<segmented>0</segmented>
	<object>
		<name>4</name>
		<pose>Unspecified</pose>
		<truncated>0</truncated>
		<difficult>0</difficult>
		<bndbox>
			<xmin>93</xmin>
			<ymin>169</ymin>
			<xmax>492</xmax>
			<ymax>545</ymax>
		</bndbox>
	</object>
	<object>
		<name>4</name>
		<pose>Unspecified</pose>
		<truncated>0</truncated>
		<difficult>0</difficult>
		<bndbox>
			<xmin>526</xmin>
			<ymin>307</ymin>
			<xmax>659</xmax>
			<ymax>466</ymax>
		</bndbox>
	</object>
	<object>
		<name>4</name>
		<pose>Unspecified</pose>
		<truncated>0</truncated>
		<difficult>0</difficult>
		<bndbox>
			<xmin>694</xmin>
			<ymin>347</ymin>
			<xmax>777</xmax>
			<ymax>459</ymax>
		</bndbox>
	</object>
</annotation>
